disneis/__init__.py
disneis/client.py
disneis/error.py
disneis/http.py
disneis/py.typed
disneis/sync.py
test/__init__.py
test/conftest.py
test/test_requests.py
disneis-4.10.1.dist-info/LICENSE
disneis-4.10.1.dist-info/METADATA
disneis-4.10.1.dist-info/WHEEL
disneis-4.10.1.dist-info/top_level.txt
disneis-4.10.1.dist-info/RECORD
