Metadata-Version: 2.1
Name: disneis
Version: 4.10.1
Summary: 나이스 api를 이용한 파이썬 모듈입니다.
Home-page: https://github.com/disocord/neispy
Author: 花 ༉ ָ࣪네먀ℓ•₯ζ°²#0919
Author-email: dofiya6199@xindax.com
License: MIT
Platform: UNKNOWN
Classifier: License :: OSI Approved :: MIT License
Classifier: Operating System :: OS Independent
Requires-Python: >=3.6
License-File: LICENSE
Requires-Dist: aiohttp
